CHANGELOG.md
neptune_f1/__init__.py
neptune_f1/domain/__init__.py
neptune_f1/domain/car_damage.py
neptune_f1/domain/car_motion.py
neptune_f1/domain/car_status.py
neptune_f1/domain/car_telemetry.py
neptune_f1/domain/cat_setup.py
neptune_f1/domain/event.py
neptune_f1/domain/final_classification.py
neptune_f1/domain/lap.py
neptune_f1/domain/lobby_info.py
neptune_f1/domain/session.py
neptune_f1/domain/session_history.py
neptune_f1/domain/utils.py
neptune_f1/packets/__init__.py
neptune_f1/packets/f12021/__init__.py
neptune_f1/packets/f12021/packet_car_damage_data.py
neptune_f1/packets/f12021/packet_car_setup_data.py
neptune_f1/packets/f12021/packet_car_status_data.py
neptune_f1/packets/f12021/packet_car_telemetry_data.py
neptune_f1/packets/f12021/packet_event_data.py
neptune_f1/packets/f12021/packet_final_classification_data.py
neptune_f1/packets/f12021/packet_header.py
neptune_f1/packets/f12021/packet_lap_data.py
neptune_f1/packets/f12021/packet_lobby_info_data.py
neptune_f1/packets/f12021/packet_motion_data.py
neptune_f1/packets/f12021/packet_participants_data.py
neptune_f1/packets/f12021/packet_session_data.py
neptune_f1/packets/f12021/packet_session_history_data.py
neptune_f1/packets/f12021/utils.py
neptune_f1/packets/factory.py
neptune_f1/packets/parser.py
neptune_f1/sources/__init__.py
neptune_f1/sources/file.py
neptune_f1/sources/old_udp_server.py
neptune_f1/sources/udp_server.py
neptune_f1-0.1.1.dist-info/LICENSE
neptune_f1-0.1.1.dist-info/WHEEL
neptune_f1-0.1.1.dist-info/METADATA
neptune_f1-0.1.1.dist-info/RECORD
