Metadata-Version: 2.1
Name: neptune-f1
Version: 0.1.1
Summary: EA F1 2021 telemetry integration with Neptune.ai
Home-page: https://github.com/Raalsky/neptune-f1
License: MIT
Author: Rafal Jankowski
Author-email: rafal@jankovsky.dev
Maintainer: Rafal Jankowski
Maintainer-email: rafal@jankovsky.dev
Requires-Python: >=3.10,<4.0
Classifier: License :: OSI Approved :: MIT License
Classifier: Programming Language :: Python :: 3
Classifier: Programming Language :: Python :: 3.10
